CHANGES.rst
LICENSE
MANIFEST.in
README.rst
setup.cfg
setup.py
tests/__init__.py
tests/strategies.py
tests/test_codefu.py
tests/test_faces.py
tests/test_mesh.py
tests/test_vertex_array.py
topos.egg-info/PKG-INFO
topos.egg-info/SOURCES.txt
topos.egg-info/dependency_links.txt
topos.egg-info/not-zip-safe
topos.egg-info/requires.txt
topos.egg-info/top_level.txt
topos/core/__init__.py
topos/core/codefu.py
topos/core/errors.py
topos/core/faces.py
topos/core/generators.py
topos/core/mesh.py
topos/core/primitives.py
topos/core/transforms.py
topos/core/version.py
topos/core/vertices.py